sage_web_apps/__init__.py
sage_web_apps/config_editor.py
sage_web_apps/config_editor_params.py
sage_web_apps/constants.py
sage_web_apps/diann_library.py
sage_web_apps/file_manager.py
sage_web_apps/msstats_convertor.py
sage_web_apps/msstats_convertor_app.py
sage_web_apps/pydantic_config.py
sage_web_apps/run.py
sage_web_apps/sage_gui.py
sage_web_apps/sage_input_app.py
sage_web_apps/sage_results_viewer.py
sage_web_apps/streamlit_utils.py
sage_web_apps/utils.py
sage_web_apps-0.6.1.dist-info/METADATA
sage_web_apps-0.6.1.dist-info/WHEEL
sage_web_apps-0.6.1.dist-info/entry_points.txt
sage_web_apps-0.6.1.dist-info/top_level.txt
sage_web_apps-0.6.1.dist-info/RECORD
