Metadata-Version: 2.4
Name: sage-web-apps
Version: 0.6.1
Summary: Web applications for Sage MS/MS search engine
Author-email: Patrick Garrett <pgarrett@scripps.edu>
Requires-Python: >=3.9
Requires-Dist: pandas
Requires-Dist: requests
Requires-Dist: streamlit>=1.45
Requires-Dist: streamlit-permalink-pg==1.5.0
Requires-Dist: platformdirs
Requires-Dist: pydantic
Requires-Dist: peptacular
Requires-Dist: streamlit-notify==0.1.1
Requires-Dist: psutil
Requires-Dist: click
Requires-Dist: rich
Requires-Dist: polars
Requires-Dist: Requests
Requires-Dist: sage_peptide_ambiguity_annotator
Requires-Dist: streamlit_notify
Provides-Extra: dev
Requires-Dist: pytest; extra == "dev"
Requires-Dist: black; extra == "dev"
